agent/README.md
agent/__main__.py
agent/agent_utils.py
agent/agents.py
agent/class_types.py
agent/cli.py
agent/display.py
agent/run_agent.py
agent/run_agent_no_rich.py
agent/configs/agent.yaml
agent/configs/base.yaml
commit0/__init__.py
commit0/__main__.py
commit0/cli.py
commit0/configs/base.yaml
commit0/configs/config_class.py
commit0/configs/user.yaml
commit0/data/test_ids/attrs.bz2
commit0/data/test_ids/babel.bz2
commit0/data/test_ids/bitstring.bz2
commit0/data/test_ids/cachetools.bz2
commit0/data/test_ids/chardet.bz2
commit0/data/test_ids/click.bz2
commit0/data/test_ids/cookiecutter.bz2
commit0/data/test_ids/deprecated.bz2
commit0/data/test_ids/dnspython.bz2
commit0/data/test_ids/dulwich.bz2
commit0/data/test_ids/fabric.bz2
commit0/data/test_ids/fastapi.bz2
commit0/data/test_ids/filesystem_spec.bz2
commit0/data/test_ids/flask.bz2
commit0/data/test_ids/geopandas.bz2
commit0/data/test_ids/graphene.bz2
commit0/data/test_ids/imapclient.bz2
commit0/data/test_ids/imbalanced-learn.bz2
commit0/data/test_ids/jedi.bz2
commit0/data/test_ids/jinja.bz2
commit0/data/test_ids/joblib.bz2
commit0/data/test_ids/loguru.bz2
commit0/data/test_ids/marshmallow.bz2
commit0/data/test_ids/mimesis.bz2
commit0/data/test_ids/minitorch.bz2
commit0/data/test_ids/more-itertools.bz2
commit0/data/test_ids/moviepy.bz2
commit0/data/test_ids/networkx.bz2
commit0/data/test_ids/paramiko.bz2
commit0/data/test_ids/parsel.bz2
commit0/data/test_ids/pexpect.bz2
commit0/data/test_ids/portalocker.bz2
commit0/data/test_ids/pyboy.bz2
commit0/data/test_ids/pydantic.bz2
commit0/data/test_ids/pyjwt.bz2
commit0/data/test_ids/pylint.bz2
commit0/data/test_ids/pypdf.bz2
commit0/data/test_ids/pytest.bz2
commit0/data/test_ids/python-progressbar.bz2
commit0/data/test_ids/python-prompt-toolkit.bz2
commit0/data/test_ids/python-rsa.bz2
commit0/data/test_ids/requests.bz2
commit0/data/test_ids/scrapy.bz2
commit0/data/test_ids/seaborn.bz2
commit0/data/test_ids/simpy.bz2
commit0/data/test_ids/sphinx.bz2
commit0-0.1.8.dist-info/METADATA
commit0-0.1.8.dist-info/WHEEL
commit0-0.1.8.dist-info/entry_points.txt
commit0-0.1.8.dist-info/licenses/LICENSE
commit0-0.1.8.dist-info/RECORD
