Metadata-Version: 2.3
Name: commit0
Version: 0.1.8
Summary: A development and evaluation framework for using language models to generate libraries.
Project-URL: Homepage, https://commit-0.github.io/
Project-URL: Repository, https://github.com/commit-0/commit0
Project-URL: Issues, https://github.com/commit-0/commit0/issues
Classifier: License :: OSI Approved :: MIT License
Requires-Python: >=3.10
Requires-Dist: datasets==3.0.1
Requires-Dist: docker>=7.1.0
Requires-Dist: fastcore>=1.7.8
Requires-Dist: ghapi>=1.0.6
Requires-Dist: gitpython>=3.1.43
Requires-Dist: modal>=0.66.26
Requires-Dist: pre-commit>=3.8.0
Requires-Dist: pytest>=8.3.3
Requires-Dist: ruff>=0.6.4
Requires-Dist: strenum>=0.4.15
Requires-Dist: typer>=0.12.0
Provides-Extra: agent
Requires-Dist: aider-chat; extra == 'agent'
Requires-Dist: import-deps>=0.3.0; extra == 'agent'
Requires-Dist: pymupdf>=1.24.5; extra == 'agent'
